[
  {
    "date": "Jul 24, 10:00 PM",
    "title": "Northern Districts Srl - Canterbury Srl",
    "bets": [
      {
        "team": "Northern Districts Srl",
        "odds": "2.24"
      },
      {
        "team": "Canterbury Srl",
        "odds": "1.6"
      }
    ]
  },
  {
    "date": "Jul 25, 12:00 AM",
    "title": "Antigua And Barbuda Falcons Srl - St Kitts And Nevis Patriots Srl",
    "bets": [
      {
        "team": "Antigua And Barbuda Falcons Srl",
        "odds": "1.89"
      },
      {
        "team": "St Kitts And Nevis Patriots Srl",
        "odds": "1.84"
      }
    ]
  },
  {
    "date": "Jul 25, 02:00 AM",
    "title": "Hobart Hurricanes Srl - Sydney Thunder Srl",
    "bets": [
      {
        "team": "Hobart Hurricanes Srl",
        "odds": "1.99"
      },
      {
        "team": "Sydney Thunder Srl",
        "odds": "1.76"
      }
    ]
  },
  {
    "date": "Jul 25, 04:00 AM",
    "title": "Peshawar Zalmi SRL - Quetta Gladiators Srl",
    "bets": [
      {
        "team": "Peshawar Zalmi Srl",
        "odds": "2.18"
      },
      {
        "team": "Quetta Gladiators Srl",
        "odds": "1.64"
      }
    ]
  },
  {
    "date": "Jul 25, 04:00 AM",
    "title": "Mis Ainak Knights - Amo Sharks",
    "bets": [
      {
        "team": "Mis Ainak Knights",
        "odds": "1.85"
      },
      {
        "team": "Amo Sharks",
        "odds": "1.85"
      }
    ]
  },
  {
    "date": "Jul 25, 06:00 AM",
    "title": "West Indies Srl - Sri Lanka Srl",
    "bets": [
      {
        "team": "West Indies Srl",
        "odds": "1.68"
      },
      {
        "team": "Sri Lanka Srl",
        "odds": "2.1"
      }
    ]
  },
  {
    "date": "Jul 25, 06:00 AM",
    "title": "Romania - Austria",
    "bets": [
      {
        "team": "Romania",
        "odds": "1.61"
      },
      {
        "team": "Austria",
        "odds": "2.17"
      }
    ]
  },
  {
    "date": "Jul 25, 06:30 AM",
    "title": "Kenya - Uganda",
    "bets": [
      {
        "team": "Kenya",
        "odds": "5.55"
      },
      {
        "team": "Uganda",
        "odds": "1.11"
      }
    ]
  },
  {
    "date": "Jul 25, 06:45 AM",
    "title": "Alby Zalmi CC - Rising Phoenix",
    "bets": [
      {
        "team": "Alby Zalmi CC",
        "odds": "1.73"
      },
      {
        "team": "Rising Phoenix",
        "odds": "1.94"
      }
    ]
  },
  {
    "date": "Jul 25, 08:00 AM",
    "title": "Gujarat Titans Srl - Rajasthan Royals SRL",
    "bets": [
      {
        "team": "Gujarat Titans Srl",
        "odds": "1.69"
      },
      {
        "team": "Rajasthan Royals SRL",
        "odds": "2.1"
      }
    ]
  },
  {
    "date": "Jul 25, 08:45 AM",
    "title": "Marsta CC - Huddinge",
    "bets": [
      {
        "team": "Marsta CC",
        "odds": "2.52"
      },
      {
        "team": "Huddinge",
        "odds": "1.44"
      }
    ]
  },
  {
    "date": "Jul 25, 09:45 AM",
    "title": "Band-e-Amir Dragons - Speen Ghar Tigers",
    "bets": [
      {
        "team": "Band-e-Amir Dragons",
        "odds": "1.51"
      },
      {
        "team": "Speen Ghar Tigers",
        "odds": "2.38"
      }
    ]
  },
  {
    "date": "Jul 25, 10:00 AM",
    "title": "Pretoria Capitals Srl - Sunrisers Eastern Cape Srl",
    "bets": [
      {
        "team": "Pretoria Capitals Srl",
        "odds": "1.96"
      },
      {
        "team": "Sunrisers Eastern Cape Srl",
        "odds": "1.78"
      }
    ]
  },
  {
    "date": "Jul 25, 10:30 AM",
    "title": "Nigeria - Namibia A",
    "bets": [
      {
        "team": "Nigeria",
        "odds": "4.16"
      },
      {
        "team": "Namibia A",
        "odds": "1.19"
      }
    ]
  },
  {
    "date": "Jul 25, 12:00 PM",
    "title": "Melbourne Renegades Srl - Sydney Thunder Srl",
    "bets": [
      {
        "team": "Melbourne Renegades Srl",
        "odds": "2.14"
      },
      {
        "team": "Sydney Thunder Srl",
        "odds": "1.66"
      }
    ]
  },
  {
    "date": "Jul 25, 01:30 PM",
    "title": "Yanam Royals - Mahe Megalo Strikers",
    "bets": [
      {
        "team": "Yanam Royals",
        "odds": "1.65"
      },
      {
        "team": "Mahe Megalo Strikers",
        "odds": "2.06"
      }
    ]
  },
  {
    "date": "Jul 25, 02:00 PM",
    "title": "Kolkata Knight Riders SRL - Punjab Kings SRL",
    "bets": [
      {
        "team": "Kolkata Knight Riders SRL",
        "odds": "2.02"
      },
      {
        "team": "Punjab Kings SRL",
        "odds": "1.75"
      }
    ]
  },
  {
    "date": "Jul 25, 03:00 PM",
    "title": "Fakhr-e-Kashmir - Royal Lions",
    "bets": [
      {
        "team": "Fakhr-e-Kashmir",
        "odds": "1.07"
      },
      {
        "team": "Royal Lions",
        "odds": "6.32"
      }
    ]
  },
  {
    "date": "Jul 25, 03:30 PM",
    "title": "Pakistan Champions - South Africa Champions",
    "bets": [
      {
        "team": "Pakistan Champions",
        "odds": "2.13"
      },
      {
        "team": "South Africa Champions",
        "odds": "1.64"
      }
    ]
  },
  {
    "date": "Jul 25, 04:00 PM",
    "title": "Multan Sultans Srl - Islamabad United Srl",
    "bets": [
      {
        "team": "Multan Sultans Srl",
        "odds": "2.12"
      },
      {
        "team": "Islamabad United Srl",
        "odds": "1.67"
      }
    ]
  },
  {
    "date": "Jul 25, 06:00 PM",
    "title": "India SRL - South Africa SRL",
    "bets": [
      {
        "team": "India Srl",
        "odds": "1.64"
      },
      {
        "team": "South Africa Srl",
        "odds": "2.18"
      }
    ]
  },
  {
    "date": "Jul 25, 07:00 PM",
    "title": "ACE KRM Panthers - Al Mulla Exchange",
    "bets": [
      {
        "team": "ACE KRM Panthers",
        "odds": "3.09"
      },
      {
        "team": "Al Mulla Exchange",
        "odds": "1.3"
      }
    ]
  },
  {
    "date": "Jul 25, 08:00 PM",
    "title": "Paarl Royals Srl - Durban Super Giants Srl",
    "bets": [
      {
        "team": "Paarl Royals Srl",
        "odds": "1.76"
      },
      {
        "team": "Durban Super Giants Srl",
        "odds": "1.99"
      }
    ]
  },
  {
    "date": "Jul 25, 10:00 PM",
    "title": "Auckland Srl - Central Districts Srl",
    "bets": [
      {
        "team": "Auckland Srl",
        "odds": "1.61"
      },
      {
        "team": "Central Districts Srl",
        "odds": "2.22"
      }
    ]
  },
  {
    "date": "Jul 25, 11:00 PM",
    "title": "West Indies - Australia",
    "bets": [
      {
        "team": "West Indies",
        "odds": "2.36"
      },
      {
        "team": "Australia",
        "odds": "1.6"
      }
    ]
  },
  {
    "date": "Jul 26, 06:00 AM",
    "title": "Malaysia - Hong Kong, China",
    "bets": [
      {
        "team": "Malaysia",
        "odds": "1.69"
      },
      {
        "team": "Hong Kong, China",
        "odds": "2"
      }
    ]
  },
  {
    "date": "Jul 26, 10:30 AM",
    "title": "Arbroath United - Grange",
    "bets": [
      {
        "team": "Arbroath United",
        "odds": "2.26"
      },
      {
        "team": "Grange",
        "odds": "1.57"
      }
    ]
  },
  {
    "date": "Jul 26, 10:30 AM",
    "title": "Carlton CC - Stewarts Melville",
    "bets": [
      {
        "team": "Carlton CC",
        "odds": "1.21"
      },
      {
        "team": "Stewarts Melville",
        "odds": "3.91"
      }
    ]
  },
  {
    "date": "Jul 26, 10:30 AM",
    "title": "Falkland - Forfarshire",
    "bets": [
      {
        "team": "Falkland",
        "odds": "2.17"
      },
      {
        "team": "Forfarshire",
        "odds": "1.61"
      }
    ]
  },
  {
    "date": "Jul 26, 10:30 AM",
    "title": "Edinburgh South - Meigle CC",
    "bets": [
      {
        "team": "Edinburgh South",
        "odds": "1.37"
      },
      {
        "team": "Meigle CC",
        "odds": "2.85"
      }
    ]
  },
  {
    "date": "Jul 26, 10:30 AM",
    "title": "RH Corstorphine - Heriots",
    "bets": [
      {
        "team": "RH Corstorphine",
        "odds": "2.67"
      },
      {
        "team": "Heriots",
        "odds": "1.41"
      }
    ]
  },
  {
    "date": "Jul 26, 11:00 AM",
    "title": "New Zealand - South Africa",
    "bets": [
      {
        "team": "New Zealand",
        "odds": "1.63"
      },
      {
        "team": "South Africa",
        "odds": "2.3"
      }
    ]
  },
  {
    "date": "Jul 26, 11:00 AM",
    "title": "TreCC Amperes - FinCC Gladiators",
    "bets": [
      {
        "team": "TreCC Amperes",
        "odds": "1.42"
      },
      {
        "team": "FinCC Gladiators",
        "odds": "2.58"
      }
    ]
  }
]